{
  "concepts": [
    {
      "id": "rl-01-the-rl-problem-s1",
      "chapter": "rl/01-the-rl-problem",
      "section": "s1",
      "title": "Agents, environments & rewards",
      "eyebrow": "REINFORCEMENT LEARNING",
      "beats": [
        {
          "text": "Reinforcement learning studies an agent that learns by interacting with an environment it cannot directly control.",
          "visual": { "type": "title", "text": "Agents, environments & rewards", "sub": "learning by interaction" }
        },
        {
          "text": "At each step the agent observes a state, chooses an action, and the environment returns a reward and a new state.",
          "visual": { "type": "lattice" }
        },
        {
          "text": "Unlike a label that names the right answer, a reward is only evaluative: it scores the action but never reveals the best one.",
          "visual": { "type": "stat", "value": 1, "label": "reward is a single scalar per step", "unit": "scalar" }
        },
        {
          "text": "Feedback is also delayed, so the agent must solve credit assignment, deciding which past decision earned a late reward.",
          "visual": { "type": "plot", "ys": [0, 0, 0, 0, 0, 1], "dot": true, "xlabel": "step", "ylabel": "reward" }
        },
        {
          "text": "The data is not fixed: the agent's own policy generates the states it sees, so improving the policy changes the data.",
          "visual": { "type": "bars", "values": [3, 1], "labels": ["RL: agent makes data", "supervised: data is fixed"], "highlight": 0 }
        },
        {
          "text": "The reward hypothesis claims any goal can be cast as maximizing expected cumulative scalar reward.",
          "visual": { "type": "title", "text": "Maximize expected cumulative reward", "sub": "the reward hypothesis" }
        }
      ]
    },
    {
      "id": "rl-01-the-rl-problem-s2",
      "chapter": "rl/01-the-rl-problem",
      "section": "s2",
      "title": "The Markov Decision Process",
      "eyebrow": "REINFORCEMENT LEARNING",
      "beats": [
        {
          "text": "The Markov decision process formalizes the interaction loop and is the common language for planning and learning.",
          "visual": { "type": "title", "text": "The Markov Decision Process", "sub": "five objects specify a world" }
        },
        {
          "text": "An MDP is a tuple of states, actions, a transition function, a reward function, and a discount factor.",
          "visual": { "type": "equation", "tex": "\\mathcal{M} = \\langle \\mathcal{S},\\ \\mathcal{A},\\ P,\\ R,\\ \\gamma \\rangle", "note": "five objects fully specify the world" }
        },
        {
          "text": "The Markov property says the current state is a sufficient statistic, so the future is independent of the past.",
          "visual": { "type": "equation", "tex": "P(s_{t+1} \\mid s_t, a_t, \\ldots, s_0) = P(s_{t+1} \\mid s_t, a_t)", "note": "history collapses into the current state" }
        },
        {
          "text": "Markovness is a property of how you define the state: stack four video frames and a single frame becomes Markov.",
          "visual": { "type": "stat", "value": 4, "label": "frames stacked to recover motion", "unit": "frames" }
        },
        {
          "text": "Transitions and rewards together form the model, and whether the agent knows them splits planning from learning.",
          "visual": { "type": "bars", "values": [1, 1], "labels": ["model known: plan", "model unknown: learn"], "highlight": 1 }
        },
        {
          "text": "In a gridworld the discount is 0.9, moving up succeeds 90 percent of the time, and each step costs 0.04.",
          "visual": { "type": "stat", "value": 0.9, "label": "P(intended move) in the slippery grid", "decimals": 2 }
        }
      ]
    },
    {
      "id": "rl-01-the-rl-problem-s3",
      "chapter": "rl/01-the-rl-problem",
      "section": "s3",
      "title": "Returns & discounting",
      "eyebrow": "REINFORCEMENT LEARNING",
      "beats": [
        {
          "text": "The agent maximizes the return, the total reward from now to the end, not just the immediate reward.",
          "visual": { "type": "title", "text": "Returns & discounting", "sub": "the agent's true objective" }
        },
        {
          "text": "The discounted return weights a reward k steps ahead by gamma to the k, keeping infinite sums finite.",
          "visual": { "type": "equation", "tex": "G_t = \\sum_{k=0}^{\\infty} \\gamma^k\\, R_{t+k+1}", "note": "bounded by R_max / (1 - gamma)" }
        },
        {
          "text": "Three consecutive rewards of one at gamma 0.9 give a return of 1 plus 0.9 plus 0.81, which is 2.71.",
          "visual": { "type": "stat", "value": 2.71, "label": "return of [1,1,1] at gamma 0.9", "decimals": 2 }
        },
        {
          "text": "Factoring out one gamma gives the recursion: this step's reward plus the discounted return of everything after.",
          "visual": { "type": "equation", "tex": "G_t = R_{t+1} + \\gamma\\, G_{t+1}", "note": "the seed of every Bellman equation" }
        },
        {
          "text": "The weight gamma to the k decays into a long tail as gamma rises, stretching how far the agent looks ahead.",
          "visual": { "type": "plot", "ys": [1, 0.9, 0.81, 0.73, 0.66, 0.59, 0.53], "xlabel": "steps ahead k", "ylabel": "weight gamma^k", "mark": true }
        },
        {
          "text": "The effective horizon one over one minus gamma is about 10 steps at 0.9 and about 100 at 0.99.",
          "visual": { "type": "bars", "values": [10, 100], "labels": ["gamma 0.9", "gamma 0.99"], "highlight": 1 }
        }
      ]
    },
    {
      "id": "rl-01-the-rl-problem-s4",
      "chapter": "rl/01-the-rl-problem",
      "section": "s4",
      "title": "Policies & value functions",
      "eyebrow": "REINFORCEMENT LEARNING",
      "beats": [
        {
          "text": "A policy maps states to actions and is the object reinforcement learning searches for, the solution to the MDP.",
          "visual": { "type": "title", "text": "Policies & value functions", "sub": "behavior, and how good it is" }
        },
        {
          "text": "A stochastic policy is a distribution over actions given the state, with the probabilities summing to one.",
          "visual": { "type": "equation", "tex": "\\pi(a \\mid s) = \\Pr(A_t = a \\mid S_t = s), \\quad \\sum_a \\pi(a \\mid s) = 1", "note": "the goal: maximize expected return" }
        },
        {
          "text": "The value functions are expected returns: V from a state under the policy, Q from a state after a chosen action.",
          "visual": { "type": "equation", "tex": "V^\\pi(s) = \\mathbb{E}_\\pi[G_t \\mid S_t = s], \\quad Q^\\pi(s,a) = \\mathbb{E}_\\pi[G_t \\mid S_t = s, A_t = a]" }
        },
        {
          "text": "The state-value is the policy-weighted average of action-values, so weight on the better action raises V.",
          "visual": { "type": "stat", "value": 9.1, "label": "V from 0.7 times 10 plus 0.3 times 7", "decimals": 1 }
        },
        {
          "text": "Knowing Q lets you act greedily without a model, which is why model-free methods learn Q rather than V.",
          "visual": { "type": "bars", "values": [10, 7, 4, 9], "labels": ["up", "down", "left", "right"], "highlight": 0 }
        },
        {
          "text": "Values are always relative to a policy, except the optimal value function, the best achievable from each state.",
          "visual": { "type": "equation", "tex": "V^{*}(s) = \\max_\\pi V^\\pi(s)", "note": "solve the MDP, read off the policy" }
        }
      ]
    },
    {
      "id": "rl-01-the-rl-problem-s5",
      "chapter": "rl/01-the-rl-problem",
      "section": "s5",
      "title": "Exploration vs exploitation",
      "eyebrow": "REINFORCEMENT LEARNING",
      "beats": [
        {
          "text": "Exploration versus exploitation is the dilemma with no counterpart in supervised learning.",
          "visual": { "type": "title", "text": "Exploration vs exploitation", "sub": "cash in, or gather information" }
        },
        {
          "text": "Exploit and you take the action you believe is best; explore and you try uncertain actions that might be better.",
          "visual": { "type": "bars", "values": [1, 1], "labels": ["exploit known", "explore unknown"], "highlight": 1 }
        },
        {
          "text": "Because the agent's actions decide its data, an action never taken is an action never learned from.",
          "visual": { "type": "lattice" }
        },
        {
          "text": "Epsilon-greedy takes the greedy action most of the time and a uniformly random action with probability epsilon.",
          "visual": { "type": "equation", "tex": "\\pi(a \\mid s) = \\begin{cases} 1 - \\varepsilon + \\frac{\\varepsilon}{|\\mathcal{A}|} & a = \\arg\\max_{a'} Q(s,a') \\\\ \\frac{\\varepsilon}{|\\mathcal{A}|} & \\text{otherwise} \\end{cases}" }
        },
        {
          "text": "With epsilon 0.1 over four actions the greedy action gets 0.925, leaving 0.075 split among the rest.",
          "visual": { "type": "stat", "value": 0.925, "label": "P(greedy) at epsilon 0.1, four actions", "decimals": 3 }
        },
        {
          "text": "Epsilon is usually annealed from high to low, and smarter schemes like UCB direct exploration toward real uncertainty.",
          "visual": { "type": "plot", "ys": [1.0, 0.78, 0.37, 0.13, 0.05, 0.05], "dot": true, "xlabel": "training step", "ylabel": "epsilon" }
        }
      ]
    }
  ]
}
